{
	"animations": [
		{
			"offsets": [0, 0],
			"indices": [],
			"fps": 24,
			"anim": "idle",
			"loop": false,
			"name": "idle"
		},
		{
			"offsets": [159, -110],
			"indices": [],
			"fps": 24,
			"anim": "singLEFT",
			"loop": false,
			"name": "singLEFT"
		},
		{
			"offsets": [71, -66],
			"indices": [],
			"fps": 24,
			"anim": "singDOWN",
			"loop": false,
			"name": "singDOWN"
		},
		{
			"offsets": [75, 25],
			"indices": [],
			"fps": 24,
			"anim": "singUP",
			"loop": false,
			"name": "singUP"
		},
		{
			"offsets": [26, -88],
			"indices": [],
			"fps": 24,
			"anim": "singRIGHT",
			"loop": false,
			"name": "singRIGHT"
		}
	],
	"vocals_file": "",
	"no_antialiasing": true,
	"image": "characters/unfair_bambi",
	"position": [-100, 50],
	"healthicon": "unfairnessexpunged",
	"flip_x": false,
	"healthbar_colors": [255, 0, 0],
	"camera_position": [-60, -160],
	"sing_duration": 4,
	"scale": 1.5,
	"_editor_isPlayer": false
}