<?xml version='1.0' encoding='utf-8'?>
<TextureAtlas imagePath="redbambi.png">
<SubTexture name="idle0000" x="0" y="316" width="328" height="281" frameX="-106" frameY="-59" frameWidth="550" frameHeight="400" />
<SubTexture name="idle0001" x="714" y="281" width="327" height="277" frameX="-94" frameY="-63" frameWidth="550" frameHeight="400" />
<SubTexture name="idle0002" x="0" y="316" width="328" height="281" frameX="-106" frameY="-59" frameWidth="550" frameHeight="400" />
<SubTexture name="idle0003" x="0" y="597" width="326" height="271" frameX="-114" frameY="-69" frameWidth="550" frameHeight="400" />
<SubTexture name="right0000" x="326" y="597" width="328" height="271" frameX="-92" frameY="-69" frameWidth="550" frameHeight="400" />
<SubTexture name="right0001" x="654" y="597" width="361" height="271" frameX="-78" frameY="-69" frameWidth="550" frameHeight="400" />
<SubTexture name="up0000" x="357" y="0" width="357" height="305" frameX="-74" frameY="-35" frameWidth="550" frameHeight="400" />
<SubTexture name="up0001" x="0" y="0" width="357" height="316" frameX="-76" frameY="-24" frameWidth="550" frameHeight="400" />
<SubTexture name="down0000" x="1063" y="0" width="322" height="255" frameX="-109" frameY="-85" frameWidth="550" frameHeight="400" />
<SubTexture name="down0001" x="1063" y="255" width="310" height="250" frameX="-108" frameY="-101" frameWidth="550" frameHeight="400" />
<SubTexture name="left0000" x="328" y="316" width="288" height="281" frameX="-117" frameY="-59" frameWidth="550" frameHeight="400" />
<SubTexture name="left0001" x="714" y="0" width="349" height="281" frameX="-83" frameY="-59" frameWidth="550" frameHeight="400" />
</TextureAtlas>
